LICENSE
MANIFEST.in
README.md
setup.py
filesystem/__init__.py
filesystem/core.py
filesystem/watcher.py
filesystem.egg-info/PKG-INFO
filesystem.egg-info/SOURCES.txt
filesystem.egg-info/dependency_links.txt
filesystem.egg-info/pbr.json
filesystem.egg-info/top_level.txt