Metadata-Version: 1.0
Name: filesystem
Version: 0.2.5
Summary: Filesystem wrapper for python developers
Home-page: https://github.com/oskarnyqvist/filesystem
Author: oskarnyqvist
Author-email: oskarnyqvist@gmail.com
License: The MIT License (MIT)
